banguard_api-0.1.5.dist-info/licenses/LICENSE
banguardapi/__init__.py
banguardapi/async_client.py
banguardapi/ban.py
banguardapi/cli.py
banguardapi/exceptions.py
banguardapi/server.py
banguardapi/sync_client.py
banguardapi/terraria_player.py
banguard_api-0.1.5.dist-info/METADATA
banguard_api-0.1.5.dist-info/WHEEL
banguard_api-0.1.5.dist-info/entry_points.txt
banguard_api-0.1.5.dist-info/top_level.txt
banguard_api-0.1.5.dist-info/RECORD
